Metadata-Version: 2.1
Name: nanoio
Version: 0.2
Summary: Minimal and fast io loop to create simple servers
Home-page: https://github.com/baverman/nanoio
Author: Anton Bobrov
Author-email: baverman@gmail.com
License: UNKNOWN
Platform: UNKNOWN
Classifier: Programming Language :: Python :: 3
Classifier: License :: OSI Approved :: MIT License
Classifier: Operating System :: OS Independent
Requires-Python: >=3.5
